{
    "images":[
        {
            "image-id": 1,
            "image-url": "https://eztees-clipart.rushordertees.com/png/32232401.x100.png"
        },
        {
            "image-id": 2,
            "image-url": "https://eztees-clipart.rushordertees.com/png/Sports09.x100.png"
        },
        {
            "image-id": 3,
            "image-url": "https://eztees-clipart.rushordertees.com/png/S_113186407.x100.png"
        },
        {
            "image-id": 4,
            "image-url": "https://eztees-clipart.rushordertees.com/png/S_49163524.x100.png"
        },
        {
            "image-id": 5,
            "image-url": "https://eztees-clipart.rushordertees.com/png/697313.x100.png"
        },
        {
            "image-id": 6,
            "image-url": "https://eztees-clipart.rushordertees.com/png/32224180.x100.png"
        },
        {
            "image-id": 7,
            "image-url": "https://eztees-clipart.rushordertees.com/png/badge1.x100.png"
        },
        {
            "image-id": 8,
            "image-url": "https://eztees-clipart.rushordertees.com/png/32449984.x100.png"
        },
        {
            "image-id": 9,
            "image-url": "https://eztees-clipart.rushordertees.com/png/nypdbg.x100.png"
        },
        {
            "image-id": 10,
            "image-url": "https://eztees-clipart.rushordertees.com/png/33041372.x100.png"
        },
        {
            "image-id": 11,
            "image-url": "https://eztees-clipart.rushordertees.com/png/S_89453110.x100.png"
        },
        {
            "image-id": 12,
            "image-url": "https://eztees-clipart.rushordertees.com/png/S_91127120.x100.png"
        },
        {
            "image-id": 13,
            "image-url": "https://eztees-clipart.rushordertees.com/png/S_30895711_3.x100.png"
        },
        {
            "image-id": 14,
            "image-url": "https://eztees-clipart.rushordertees.com/png/32232069.x100.png"
        },
        {
            "image-id": 15,
            "image-url": "https://eztees-clipart.rushordertees.com/png/32447025.x100.png"
        },
        {
            "image-id": 16,
            "image-url": "https://eztees-clipart.rushordertees.com/png/32205995.x100.png"
        },
        {
            "image-id": 17,
            "image-url": "https://eztees-clipart.rushordertees.com/png/shield_06.x100.png"
        },
        {
            "image-id": 18,
            "image-url": "https://eztees-clipart.rushordertees.com/png/shield_08.x100.png"
        },
        {
            "image-id": 19,
            "image-url": "https://eztees-clipart.rushordertees.com/png/shield_02.x100.png"
        },
        {
            "image-id": 20,
            "image-url": "https://eztees-clipart.rushordertees.com/png/shield_04.x100.png"
        },
        {
            "image-id": 21,
            "image-url": "https://eztees-clipart.rushordertees.com/png/shield_01.x100.png"
        },
        {
            "image-id": 22,
            "image-url": "https://eztees-clipart.rushordertees.com/png/shield_03.x100.png"
        },
        {
            "image-id": 23,
            "image-url": "https://eztees-clipart.rushordertees.com/png/shield_07.x100.png"
        },
        {
            "image-id": 24,
            "image-url": "https://eztees-clipart.rushordertees.com/png/shield_05.x100.png"
        },
        {
            "image-id": 25,
            "image-url": "https://eztees-clipart.rushordertees.com/png/shield_09.x100.png"
        },
        {
            "image-id": 26,
            "image-url": "https://eztees-clipart.rushordertees.com/png/shield_10.x100.png"
        },
        {
            "image-id": 27,
            "image-url": "https://eztees-clipart.rushordertees.com/png/shield_11.x100.png"
        },
        {
            "image-id": 28,
            "image-url": "https://eztees-clipart.rushordertees.com/png/shield_12.x100.png"
        },
        {
            "image-id": 29,
            "image-url": "https://eztees-clipart.rushordertees.com/png/16118128.x100.png"
        },
        {
            "image-id": 30,
            "image-url": "https://eztees-clipart.rushordertees.com/png/32223770.x100.png"
        },
        {
            "image-id": 31,
            "image-url": "https://eztees-clipart.rushordertees.com/png/697331.x100.png"
        },
        {
            "image-id": 32,
            "image-url": "https://eztees-clipart.rushordertees.com/png/32223268.x100.png"
        },
        {
            "image-id": 33,
            "image-url": "https://eztees-clipart.rushordertees.com/png/32225707.x100.png"
        },
        {
            "image-id": 34,
            "image-url": "https://eztees-clipart.rushordertees.com/png/32205474.x100.png"
        },
        {
            "image-id": 35,
            "image-url": "https://eztees-clipart.rushordertees.com/png/32223271.x100.png"
        },
        {
            "image-id": 36,
            "image-url": "https://eztees-clipart.rushordertees.com/png/33041415.x100.png"
        },
        {
            "image-id": 37,
            "image-url": "https://eztees-clipart.rushordertees.com/png/33041401.x100.png"
        },
        {
            "image-id": 38,
            "image-url": "https://eztees-clipart.rushordertees.com/png/32251718.x100.png"
        }]
}